skanym_gui/__init__.py
skanym_gui/__main__.py
skanym_gui/frame.py
skanym_gui/init.py
skanym_gui/main.xml
skanym_gui/size.py
skanym_gui/assets/shaders/lighting_prog_ps_gl21.glsl
skanym_gui/assets/shaders/lighting_prog_ps_gl32.glsl
skanym_gui/assets/shaders/lighting_prog_vs_gl21.glsl
skanym_gui/assets/shaders/lighting_prog_vs_gl32.glsl
skanym_gui/assets/textures/white_black_border.jpg
skanym_gui-0.0.8.dist-info/LICENSE.txt
skanym_gui-0.0.8.dist-info/METADATA
skanym_gui-0.0.8.dist-info/WHEEL
skanym_gui-0.0.8.dist-info/entry_points.txt
skanym_gui-0.0.8.dist-info/top_level.txt
skanym_gui-0.0.8.dist-info/RECORD
