Metadata-Version: 2.1
Name: skanym_gui
Version: 0.0.8
Summary: gui extension for skanym using GeeXLab engine
Author-email: Dimitri Kohler <dimitri.kohler@he-arc.ch>
License: MIT License
Project-URL: Repository, https://gitlab-etu.ing.he-arc.ch/isc/general/motion-machine/skanym-package/skanym-gui
Classifier: Development Status :: 4 - Beta
Classifier: Intended Audience :: Developers
Classifier: Topic :: Software Development
Classifier: Programming Language :: Python :: 3.10
Requires-Python: ==3.10.*
License-File: LICENSE.txt
